ha_geo_detector/__init__.py
ha_geo_detector/run.py
ha_geo_detector/data/.DS_Store
ha_geo_detector/data/blacklisted_codes.txt
ha_geo_detector/data/blacklisted_domains.txt
ha_geo_detector/data/blacklisted_names.txt
ha_geo_detector/data/cities15000.txt
ha_geo_detector/data/countryInfo.txt
ha_geo_detector/data/domains_freq.tsv
ha_geo_detector/data/nations.tsv
ha_geo_detector/data/rg_cities1000.csv
ha_geo_detector/data/rg_cities1000_copy.csv
ha_geo_detector/data/states.tsv
ha_geo_detector/service/__init__.py
ha_geo_detector/service/additional.py
ha_geo_detector/service/build.py
ha_geo_detector/service/detect.py
ha_geo_detector/service/service.py
ha_geo_detector-2.dist-info/METADATA
ha_geo_detector-2.dist-info/WHEEL
ha_geo_detector-2.dist-info/top_level.txt
ha_geo_detector-2.dist-info/RECORD
